LICENSE
setup.py
pyroplus/__init__.py
pyroplus/client.py
pyroplus/dispatcher.py
pyroplus/emoji.py
pyroplus/file_id.py
pyroplus/filters.py
pyroplus/mime_types.py
pyroplus/sync.py
pyroplus/utils.py
pyroplus.egg-info/PKG-INFO
pyroplus.egg-info/SOURCES.txt
pyroplus.egg-info/dependency_links.txt
pyroplus.egg-info/top_level.txt
pyroplus/connection/__init__.py
pyroplus/connection/connection.py
pyroplus/connection/transport/__init__.py
pyroplus/connection/transport/tcp/__init__.py
pyroplus/connection/transport/tcp/tcp.py
pyroplus/connection/transport/tcp/tcp_abridged.py
pyroplus/connection/transport/tcp/tcp_abridged_o.py
pyroplus/connection/transport/tcp/tcp_full.py
pyroplus/connection/transport/tcp/tcp_intermediate.py
pyroplus/connection/transport/tcp/tcp_intermediate_o.py
pyroplus/crypto/__init__.py
pyroplus/crypto/aes.py
pyroplus/crypto/mtproto.py
pyroplus/crypto/prime.py
pyroplus/crypto/rsa.py
pyroplus/enums/__init__.py
pyroplus/enums/auto_name.py
pyroplus/enums/chat_action.py
pyroplus/enums/chat_event_action.py
pyroplus/enums/chat_member_status.py
pyroplus/enums/chat_members_filter.py
pyroplus/enums/chat_type.py
pyroplus/enums/message_entity_type.py
pyroplus/enums/message_media_type.py
pyroplus/enums/message_service_type.py
pyroplus/enums/messages_filter.py
pyroplus/enums/next_code_type.py
pyroplus/enums/parse_mode.py
pyroplus/enums/poll_type.py
pyroplus/enums/sent_code_type.py
pyroplus/enums/user_status.py
pyroplus/errors/__init__.py
pyroplus/errors/rpc_error.py
pyroplus/errors/exceptions/__init__.py
pyroplus/errors/exceptions/all.py
pyroplus/errors/exceptions/bad_request_400.py
pyroplus/errors/exceptions/flood_420.py
pyroplus/errors/exceptions/forbidden_403.py
pyroplus/errors/exceptions/internal_server_error_500.py
pyroplus/errors/exceptions/not_acceptable_406.py
pyroplus/errors/exceptions/see_other_303.py
pyroplus/errors/exceptions/service_unavailable_503.py
pyroplus/errors/exceptions/unauthorized_401.py
pyroplus/handlers/__init__.py
pyroplus/handlers/callback_query_handler.py
pyroplus/handlers/chat_join_request_handler.py
pyroplus/handlers/chat_member_updated_handler.py
